[
    {
        "Hora": "28-08-2024 08:48:35",
        "Download (MB)": 0.0,
        "Upload (MB)": 0.0
    },
    {
        "Hora": "28-08-2024 08:48:36",
        "Download (MB)": 0.0,
        "Upload (MB)": 0.0
    },
    {
        "Hora": "28-08-2024 08:48:37",
        "Download (MB)": 0.01,
        "Upload (MB)": 0.01
    },
    {
        "Hora": "28-08-2024 08:48:38",
        "Download (MB)": 0.01,
        "Upload (MB)": 0.0
    },
    {
        "Hora": "28-08-2024 08:48:39",
        "Download (MB)": 0.0,
        "Upload (MB)": 0.0
    },
    {
        "Hora": "28-08-2024 08:48:40",
        "Download (MB)": 0.0,
        "Upload (MB)": 0.0
    },
    {
        "Hora": "28-08-2024 08:48:41",
        "Download (MB)": 0.0,
        "Upload (MB)": 0.0
    },
    {
        "Hora": "28-08-2024 08:48:42",
        "Download (MB)": 0.02,
        "Upload (MB)": 0.02
    },
    {
        "Hora": "28-08-2024 08:48:43",
        "Download (MB)": 0.01,
        "Upload (MB)": 0.01
    },
    {
        "Hora": "28-08-2024 08:48:44",
        "Download (MB)": 0.01,
        "Upload (MB)": 0.01
    },
    {
        "Hora": "28-08-2024 08:48:45",
        "Download (MB)": 0.01,
        "Upload (MB)": 0.01
    },
    {
        "Hora": "28-08-2024 13:07:40",
        "Download (MB)": 1.32,
        "Upload (MB)": 2.19
    },
    {
        "Hora": "28-08-2024 13:07:41",
        "Download (MB)": 0.91,
        "Upload (MB)": 1.67
    },
    {
        "Hora": "28-08-2024 13:07:51",
        "Download (MB)": 1.26,
        "Upload (MB)": 1.8
    },
    {
        "Hora": "28-08-2024 14:17:04",
        "Download (MB)": 1.52,
        "Upload (MB)": 2.54
    },
    {
        "Hora": "28-08-2024 14:17:05",
        "Download (MB)": 0.68,
        "Upload (MB)": 1.34
    },
    {
        "Hora": "28-08-2024 14:17:38",
        "Download (MB)": 1.08,
        "Upload (MB)": 1.73
    },
    {
        "Hora": "28-08-2024 14:17:39",
        "Download (MB)": 1.12,
        "Upload (MB)": 2.08
    },
    {
        "Hora": "28-08-2024 15:09:47",
        "Download (MB)": 33.69,
        "Upload (MB)": 0.98
    },
    {
        "Hora": "28-08-2024 15:09:48",
        "Download (MB)": 69.35,
        "Upload (MB)": 1.8
    },
    {
        "Hora": "28-08-2024 15:09:48",
        "Download (MB)": 93.62,
        "Upload (MB)": 2.05
    },
    {
        "Hora": "28-08-2024 15:09:49",
        "Download (MB)": 96.62,
        "Upload (MB)": 1.87
    },
    {
        "Hora": "28-08-2024 15:09:49",
        "Download (MB)": 89.89,
        "Upload (MB)": 1.59
    },
    {
        "Hora": "28-08-2024 15:09:50",
        "Download (MB)": 89.31,
        "Upload (MB)": 1.75
    },
    {
        "Hora": "28-08-2024 15:09:50",
        "Download (MB)": 92.83,
        "Upload (MB)": 1.76
    },
    {
        "Hora": "28-08-2024 15:09:51",
        "Download (MB)": 88.78,
        "Upload (MB)": 1.71
    },
    {
        "Hora": "28-08-2024 15:09:51",
        "Download (MB)": 80.52,
        "Upload (MB)": 1.75
    },
    {
        "Hora": "28-08-2024 15:09:52",
        "Download (MB)": 70.0,
        "Upload (MB)": 1.53
    },
    {
        "Hora": "28-08-2024 15:09:52",
        "Download (MB)": 23.67,
        "Upload (MB)": 6.02
    },
    {
        "Hora": "28-08-2024 15:09:53",
        "Download (MB)": 0.61,
        "Upload (MB)": 34.15
    },
    {
        "Hora": "28-08-2024 15:09:53",
        "Download (MB)": 1.12,
        "Upload (MB)": 77.53
    },
    {
        "Hora": "28-08-2024 15:09:54",
        "Download (MB)": 1.07,
        "Upload (MB)": 81.7
    },
    {
        "Hora": "28-08-2024 15:09:54",
        "Download (MB)": 0.83,
        "Upload (MB)": 70.82
    },
    {
        "Hora": "28-08-2024 15:09:55",
        "Download (MB)": 0.43,
        "Upload (MB)": 38.44
    },
    {
        "Hora": "28-08-2024 15:10:13",
        "Download (MB)": 8.73,
        "Upload (MB)": 0.2
    },
    {
        "Hora": "28-08-2024 15:10:13",
        "Download (MB)": 65.02,
        "Upload (MB)": 1.61
    },
    {
        "Hora": "28-08-2024 15:10:14",
        "Download (MB)": 99.11,
        "Upload (MB)": 2.16
    },
    {
        "Hora": "28-08-2024 15:10:14",
        "Download (MB)": 97.47,
        "Upload (MB)": 1.82
    },
    {
        "Hora": "28-08-2024 15:10:15",
        "Download (MB)": 90.6,
        "Upload (MB)": 1.85
    },
    {
        "Hora": "28-08-2024 15:10:15",
        "Download (MB)": 96.16,
        "Upload (MB)": 1.78
    },
    {
        "Hora": "28-08-2024 15:10:16",
        "Download (MB)": 102.66,
        "Upload (MB)": 1.68
    },
    {
        "Hora": "28-08-2024 15:10:16",
        "Download (MB)": 108.33,
        "Upload (MB)": 1.61
    },
    {
        "Hora": "28-08-2024 15:10:17",
        "Download (MB)": 105.98,
        "Upload (MB)": 1.7
    },
    {
        "Hora": "28-08-2024 15:10:17",
        "Download (MB)": 47.2,
        "Upload (MB)": 2.73
    },
    {
        "Hora": "28-08-2024 15:10:18",
        "Download (MB)": 7.97,
        "Upload (MB)": 26.79
    },
    {
        "Hora": "28-08-2024 15:10:18",
        "Download (MB)": 1.58,
        "Upload (MB)": 81.93
    },
    {
        "Hora": "28-08-2024 15:10:19",
        "Download (MB)": 1.2,
        "Upload (MB)": 91.98
    },
    {
        "Hora": "28-08-2024 15:10:19",
        "Download (MB)": 0.89,
        "Upload (MB)": 71.17
    },
    {
        "Hora": "28-08-2024 15:10:20",
        "Download (MB)": 0.42,
        "Upload (MB)": 36.31
    },
    {
        "Hora": "28-08-2024 15:10:32",
        "Download (MB)": 30.69,
        "Upload (MB)": 0.79
    },
    {
        "Hora": "28-08-2024 15:10:33",
        "Download (MB)": 67.38,
        "Upload (MB)": 1.57
    },
    {
        "Hora": "28-08-2024 15:10:33",
        "Download (MB)": 96.66,
        "Upload (MB)": 1.97
    },
    {
        "Hora": "28-08-2024 15:10:34",
        "Download (MB)": 102.82,
        "Upload (MB)": 1.89
    },
    {
        "Hora": "28-08-2024 15:10:34",
        "Download (MB)": 111.41,
        "Upload (MB)": 1.63
    },
    {
        "Hora": "28-08-2024 15:10:35",
        "Download (MB)": 109.91,
        "Upload (MB)": 1.62
    },
    {
        "Hora": "28-08-2024 15:10:35",
        "Download (MB)": 102.2,
        "Upload (MB)": 1.95
    },
    {
        "Hora": "28-08-2024 15:10:36",
        "Download (MB)": 95.3,
        "Upload (MB)": 1.95
    },
    {
        "Hora": "28-08-2024 15:10:36",
        "Download (MB)": 73.19,
        "Upload (MB)": 1.61
    },
    {
        "Hora": "28-08-2024 15:10:37",
        "Download (MB)": 38.73,
        "Upload (MB)": 0.93
    },
    {
        "Hora": "28-08-2024 15:10:37",
        "Download (MB)": 1.17,
        "Upload (MB)": 36.74
    },
    {
        "Hora": "28-08-2024 15:10:38",
        "Download (MB)": 1.6,
        "Upload (MB)": 69.87
    },
    {
        "Hora": "28-08-2024 15:10:38",
        "Download (MB)": 1.51,
        "Upload (MB)": 112.17
    },
    {
        "Hora": "28-08-2024 15:10:39",
        "Download (MB)": 1.14,
        "Upload (MB)": 83.82
    },
    {
        "Hora": "28-08-2024 15:10:39",
        "Download (MB)": 0.09,
        "Upload (MB)": 4.84
    },
    {
        "Hora": "28-08-2024 15:10:46",
        "Download (MB)": 3.13,
        "Upload (MB)": 0.12
    },
    {
        "Hora": "28-08-2024 15:10:46",
        "Download (MB)": 67.58,
        "Upload (MB)": 1.36
    },
    {
        "Hora": "28-08-2024 15:10:47",
        "Download (MB)": 94.19,
        "Upload (MB)": 1.78
    },
    {
        "Hora": "28-08-2024 15:10:47",
        "Download (MB)": 109.21,
        "Upload (MB)": 2.19
    },
    {
        "Hora": "28-08-2024 15:10:48",
        "Download (MB)": 109.26,
        "Upload (MB)": 2.07
    },
    {
        "Hora": "28-08-2024 15:10:48",
        "Download (MB)": 110.06,
        "Upload (MB)": 2.04
    },
    {
        "Hora": "28-08-2024 15:10:49",
        "Download (MB)": 111.41,
        "Upload (MB)": 2.31
    },
    {
        "Hora": "28-08-2024 15:10:49",
        "Download (MB)": 110.04,
        "Upload (MB)": 2.13
    },
    {
        "Hora": "28-08-2024 15:10:50",
        "Download (MB)": 96.11,
        "Upload (MB)": 1.81
    },
    {
        "Hora": "28-08-2024 15:10:50",
        "Download (MB)": 17.23,
        "Upload (MB)": 0.38
    },
    {
        "Hora": "28-08-2024 15:10:51",
        "Download (MB)": 0.08,
        "Upload (MB)": 5.95
    },
    {
        "Hora": "28-08-2024 15:10:52",
        "Download (MB)": 0.22,
        "Upload (MB)": 23.38
    },
    {
        "Hora": "28-08-2024 15:10:52",
        "Download (MB)": 0.54,
        "Upload (MB)": 84.09
    },
    {
        "Hora": "28-08-2024 15:10:53",
        "Download (MB)": 0.6,
        "Upload (MB)": 98.2
    },
    {
        "Hora": "28-08-2024 15:10:53",
        "Download (MB)": 0.4,
        "Upload (MB)": 63.38
    },
    {
        "Hora": "28-08-2024 15:10:54",
        "Download (MB)": 0.21,
        "Upload (MB)": 31.84
    },
    {
        "Hora": "28-08-2024 15:11:01",
        "Download (MB)": 4.7,
        "Upload (MB)": 0.2
    },
    {
        "Hora": "28-08-2024 15:11:02",
        "Download (MB)": 24.74,
        "Upload (MB)": 0.78
    },
    {
        "Hora": "28-08-2024 15:11:02",
        "Download (MB)": 90.68,
        "Upload (MB)": 2.0
    },
    {
        "Hora": "28-08-2024 15:11:03",
        "Download (MB)": 94.65,
        "Upload (MB)": 1.91
    },
    {
        "Hora": "28-08-2024 15:11:03",
        "Download (MB)": 82.1,
        "Upload (MB)": 1.73
    },
    {
        "Hora": "28-08-2024 15:11:04",
        "Download (MB)": 77.93,
        "Upload (MB)": 1.63
    },
    {
        "Hora": "28-08-2024 15:11:04",
        "Download (MB)": 69.99,
        "Upload (MB)": 1.56
    },
    {
        "Hora": "28-08-2024 15:11:05",
        "Download (MB)": 71.4,
        "Upload (MB)": 1.63
    },
    {
        "Hora": "28-08-2024 15:11:05",
        "Download (MB)": 75.95,
        "Upload (MB)": 1.66
    },
    {
        "Hora": "28-08-2024 15:11:06",
        "Download (MB)": 75.15,
        "Upload (MB)": 1.63
    },
    {
        "Hora": "28-08-2024 15:11:06",
        "Download (MB)": 74.34,
        "Upload (MB)": 1.57
    },
    {
        "Hora": "28-08-2024 15:11:07",
        "Download (MB)": 65.99,
        "Upload (MB)": 1.42
    },
    {
        "Hora": "28-08-2024 15:11:07",
        "Download (MB)": 16.62,
        "Upload (MB)": 4.61
    },
    {
        "Hora": "28-08-2024 15:11:08",
        "Download (MB)": 5.12,
        "Upload (MB)": 19.48
    },
    {
        "Hora": "28-08-2024 15:11:08",
        "Download (MB)": 1.96,
        "Upload (MB)": 85.42
    },
    {
        "Hora": "28-08-2024 15:11:09",
        "Download (MB)": 1.55,
        "Upload (MB)": 87.85
    },
    {
        "Hora": "28-08-2024 15:11:10",
        "Download (MB)": 0.75,
        "Upload (MB)": 62.97
    },
    {
        "Hora": "28-08-2024 15:11:10",
        "Download (MB)": 0.58,
        "Upload (MB)": 46.98
    },
    {
        "Hora": "28-08-2024 16:21:08",
        "Download (MB)": 3.08,
        "Upload (MB)": 0.11
    },
    {
        "Hora": "28-08-2024 16:21:09",
        "Download (MB)": 42.07,
        "Upload (MB)": 0.94
    },
    {
        "Hora": "28-08-2024 16:21:09",
        "Download (MB)": 96.26,
        "Upload (MB)": 1.31
    },
    {
        "Hora": "28-08-2024 16:21:10",
        "Download (MB)": 98.48,
        "Upload (MB)": 1.27
    },
    {
        "Hora": "28-08-2024 16:21:10",
        "Download (MB)": 95.06,
        "Upload (MB)": 1.48
    },
    {
        "Hora": "28-08-2024 16:21:11",
        "Download (MB)": 92.93,
        "Upload (MB)": 1.11
    },
    {
        "Hora": "28-08-2024 16:21:11",
        "Download (MB)": 91.85,
        "Upload (MB)": 1.34
    },
    {
        "Hora": "28-08-2024 16:21:12",
        "Download (MB)": 101.41,
        "Upload (MB)": 1.61
    },
    {
        "Hora": "28-08-2024 16:21:12",
        "Download (MB)": 103.99,
        "Upload (MB)": 1.09
    },
    {
        "Hora": "28-08-2024 16:21:13",
        "Download (MB)": 73.75,
        "Upload (MB)": 0.68
    },
    {
        "Hora": "28-08-2024 16:21:13",
        "Download (MB)": 18.76,
        "Upload (MB)": 10.79
    },
    {
        "Hora": "28-08-2024 16:21:14",
        "Download (MB)": 1.11,
        "Upload (MB)": 36.67
    },
    {
        "Hora": "28-08-2024 16:21:14",
        "Download (MB)": 1.61,
        "Upload (MB)": 57.8
    },
    {
        "Hora": "28-08-2024 16:21:15",
        "Download (MB)": 1.49,
        "Upload (MB)": 56.93
    },
    {
        "Hora": "28-08-2024 16:21:15",
        "Download (MB)": 1.97,
        "Upload (MB)": 74.72
    },
    {
        "Hora": "28-08-2024 16:21:16",
        "Download (MB)": 1.56,
        "Upload (MB)": 59.09
    },
    {
        "Hora": "28-08-2024 16:21:16",
        "Download (MB)": 0.28,
        "Upload (MB)": 10.16
    },
    {
        "Hora": "28-08-2024 16:21:20",
        "Download (MB)": 16.76,
        "Upload (MB)": 0.49
    },
    {
        "Hora": "28-08-2024 16:21:20",
        "Download (MB)": 77.48,
        "Upload (MB)": 1.74
    },
    {
        "Hora": "28-08-2024 16:21:21",
        "Download (MB)": 108.68,
        "Upload (MB)": 2.05
    },
    {
        "Hora": "28-08-2024 16:21:21",
        "Download (MB)": 110.92,
        "Upload (MB)": 2.04
    },
    {
        "Hora": "28-08-2024 16:21:22",
        "Download (MB)": 103.69,
        "Upload (MB)": 2.22
    },
    {
        "Hora": "28-08-2024 16:21:22",
        "Download (MB)": 106.32,
        "Upload (MB)": 1.73
    },
    {
        "Hora": "28-08-2024 16:21:23",
        "Download (MB)": 111.87,
        "Upload (MB)": 1.45
    },
    {
        "Hora": "28-08-2024 16:21:23",
        "Download (MB)": 109.38,
        "Upload (MB)": 1.86
    },
    {
        "Hora": "28-08-2024 16:21:24",
        "Download (MB)": 73.17,
        "Upload (MB)": 1.32
    },
    {
        "Hora": "28-08-2024 16:21:24",
        "Download (MB)": 10.24,
        "Upload (MB)": 18.63
    },
    {
        "Hora": "28-08-2024 16:21:25",
        "Download (MB)": 0.54,
        "Upload (MB)": 59.05
    },
    {
        "Hora": "28-08-2024 16:21:25",
        "Download (MB)": 0.75,
        "Upload (MB)": 102.2
    },
    {
        "Hora": "28-08-2024 16:21:26",
        "Download (MB)": 0.58,
        "Upload (MB)": 93.54
    },
    {
        "Hora": "28-08-2024 16:21:26",
        "Download (MB)": 0.22,
        "Upload (MB)": 32.9
    },
    {
        "Hora": "28-08-2024 16:21:30",
        "Download (MB)": 2.3,
        "Upload (MB)": 0.09
    },
    {
        "Hora": "28-08-2024 16:21:30",
        "Download (MB)": 60.37,
        "Upload (MB)": 1.15
    },
    {
        "Hora": "28-08-2024 16:21:31",
        "Download (MB)": 99.44,
        "Upload (MB)": 1.81
    },
    {
        "Hora": "28-08-2024 16:21:31",
        "Download (MB)": 108.26,
        "Upload (MB)": 1.45
    },
    {
        "Hora": "28-08-2024 16:21:32",
        "Download (MB)": 109.78,
        "Upload (MB)": 1.41
    },
    {
        "Hora": "28-08-2024 16:21:32",
        "Download (MB)": 108.99,
        "Upload (MB)": 1.72
    },
    {
        "Hora": "28-08-2024 16:21:33",
        "Download (MB)": 108.58,
        "Upload (MB)": 1.61
    },
    {
        "Hora": "28-08-2024 16:21:33",
        "Download (MB)": 109.2,
        "Upload (MB)": 1.53
    },
    {
        "Hora": "28-08-2024 16:21:34",
        "Download (MB)": 83.72,
        "Upload (MB)": 1.24
    },
    {
        "Hora": "28-08-2024 16:21:34",
        "Download (MB)": 22.85,
        "Upload (MB)": 0.47
    },
    {
        "Hora": "28-08-2024 16:21:35",
        "Download (MB)": 6.36,
        "Upload (MB)": 17.85
    },
    {
        "Hora": "28-08-2024 16:21:35",
        "Download (MB)": 1.96,
        "Upload (MB)": 72.78
    },
    {
        "Hora": "28-08-2024 16:21:36",
        "Download (MB)": 2.02,
        "Upload (MB)": 77.21
    },
    {
        "Hora": "28-08-2024 16:21:36",
        "Download (MB)": 1.89,
        "Upload (MB)": 74.19
    },
    {
        "Hora": "28-08-2024 16:21:37",
        "Download (MB)": 1.5,
        "Upload (MB)": 58.12
    },
    {
        "Hora": "28-08-2024 16:21:37",
        "Download (MB)": 0.21,
        "Upload (MB)": 6.13
    },
    {
        "Hora": "28-08-2024 16:21:41",
        "Download (MB)": 27.71,
        "Upload (MB)": 0.66
    },
    {
        "Hora": "28-08-2024 16:21:42",
        "Download (MB)": 64.7,
        "Upload (MB)": 1.19
    },
    {
        "Hora": "28-08-2024 16:21:42",
        "Download (MB)": 110.78,
        "Upload (MB)": 1.38
    },
    {
        "Hora": "28-08-2024 16:21:43",
        "Download (MB)": 112.57,
        "Upload (MB)": 1.2
    },
    {
        "Hora": "28-08-2024 16:21:43",
        "Download (MB)": 110.88,
        "Upload (MB)": 1.47
    },
    {
        "Hora": "28-08-2024 16:21:44",
        "Download (MB)": 108.2,
        "Upload (MB)": 1.38
    },
    {
        "Hora": "28-08-2024 16:21:45",
        "Download (MB)": 107.92,
        "Upload (MB)": 1.46
    },
    {
        "Hora": "28-08-2024 16:21:45",
        "Download (MB)": 104.43,
        "Upload (MB)": 1.7
    },
    {
        "Hora": "28-08-2024 16:21:46",
        "Download (MB)": 51.41,
        "Upload (MB)": 0.92
    },
    {
        "Hora": "28-08-2024 16:21:46",
        "Download (MB)": 19.05,
        "Upload (MB)": 9.52
    },
    {
        "Hora": "28-08-2024 16:21:47",
        "Download (MB)": 1.49,
        "Upload (MB)": 49.91
    },
    {
        "Hora": "28-08-2024 16:21:47",
        "Download (MB)": 1.78,
        "Upload (MB)": 62.33
    },
    {
        "Hora": "28-08-2024 16:21:48",
        "Download (MB)": 1.65,
        "Upload (MB)": 62.66
    },
    {
        "Hora": "28-08-2024 16:21:48",
        "Download (MB)": 1.52,
        "Upload (MB)": 56.14
    },
    {
        "Hora": "28-08-2024 16:21:49",
        "Download (MB)": 1.09,
        "Upload (MB)": 40.55
    },
    {
        "Hora": "28-08-2024 16:21:49",
        "Download (MB)": 0.68,
        "Upload (MB)": 25.51
    },
    {
        "Hora": "28-08-2024 16:21:53",
        "Download (MB)": 52.95,
        "Upload (MB)": 1.18
    },
    {
        "Hora": "28-08-2024 16:21:53",
        "Download (MB)": 81.25,
        "Upload (MB)": 1.56
    },
    {
        "Hora": "28-08-2024 16:21:54",
        "Download (MB)": 110.01,
        "Upload (MB)": 1.62
    },
    {
        "Hora": "28-08-2024 16:21:54",
        "Download (MB)": 108.83,
        "Upload (MB)": 1.47
    },
    {
        "Hora": "28-08-2024 16:21:55",
        "Download (MB)": 112.12,
        "Upload (MB)": 1.55
    },
    {
        "Hora": "28-08-2024 16:21:55",
        "Download (MB)": 109.87,
        "Upload (MB)": 1.65
    },
    {
        "Hora": "28-08-2024 16:21:56",
        "Download (MB)": 107.92,
        "Upload (MB)": 1.31
    },
    {
        "Hora": "28-08-2024 16:21:56",
        "Download (MB)": 105.57,
        "Upload (MB)": 1.29
    },
    {
        "Hora": "28-08-2024 16:21:57",
        "Download (MB)": 25.84,
        "Upload (MB)": 9.77
    },
    {
        "Hora": "28-08-2024 16:21:57",
        "Download (MB)": 3.62,
        "Upload (MB)": 20.0
    },
    {
        "Hora": "28-08-2024 16:21:58",
        "Download (MB)": 2.05,
        "Upload (MB)": 74.52
    },
    {
        "Hora": "28-08-2024 16:21:58",
        "Download (MB)": 2.18,
        "Upload (MB)": 80.65
    },
    {
        "Hora": "28-08-2024 16:21:59",
        "Download (MB)": 1.69,
        "Upload (MB)": 67.02
    },
    {
        "Hora": "28-08-2024 16:21:59",
        "Download (MB)": 1.31,
        "Upload (MB)": 52.27
    },
    {
        "Hora": "28-08-2024 16:22:00",
        "Download (MB)": 0.09,
        "Upload (MB)": 1.98
    },
    {
        "Hora": "28-08-2024 16:31:02",
        "Download (MB)": 30.72,
        "Upload (MB)": 0.76
    },
    {
        "Hora": "28-08-2024 16:31:02",
        "Download (MB)": 92.26,
        "Upload (MB)": 1.78
    },
    {
        "Hora": "28-08-2024 16:31:03",
        "Download (MB)": 111.7,
        "Upload (MB)": 1.73
    },
    {
        "Hora": "28-08-2024 16:31:03",
        "Download (MB)": 111.62,
        "Upload (MB)": 1.1
    },
    {
        "Hora": "28-08-2024 16:31:04",
        "Download (MB)": 102.11,
        "Upload (MB)": 0.66
    },
    {
        "Hora": "28-08-2024 16:31:04",
        "Download (MB)": 103.16,
        "Upload (MB)": 0.83
    },
    {
        "Hora": "28-08-2024 16:31:05",
        "Download (MB)": 111.65,
        "Upload (MB)": 1.1
    },
    {
        "Hora": "28-08-2024 16:31:05",
        "Download (MB)": 98.97,
        "Upload (MB)": 1.29
    },
    {
        "Hora": "28-08-2024 16:31:06",
        "Download (MB)": 52.46,
        "Upload (MB)": 0.8
    },
    {
        "Hora": "28-08-2024 16:31:06",
        "Download (MB)": 3.35,
        "Upload (MB)": 24.09
    },
    {
        "Hora": "28-08-2024 16:31:07",
        "Download (MB)": 1.65,
        "Upload (MB)": 58.03
    },
    {
        "Hora": "28-08-2024 16:31:07",
        "Download (MB)": 2.0,
        "Upload (MB)": 75.04
    },
    {
        "Hora": "28-08-2024 16:31:08",
        "Download (MB)": 2.09,
        "Upload (MB)": 80.73
    },
    {
        "Hora": "28-08-2024 16:31:08",
        "Download (MB)": 1.36,
        "Upload (MB)": 53.54
    },
    {
        "Hora": "28-08-2024 16:31:09",
        "Download (MB)": 0.38,
        "Upload (MB)": 13.93
    },
    {
        "Hora": "28-08-2024 16:31:13",
        "Download (MB)": 19.12,
        "Upload (MB)": 0.57
    },
    {
        "Hora": "28-08-2024 16:31:13",
        "Download (MB)": 80.09,
        "Upload (MB)": 1.62
    },
    {
        "Hora": "28-08-2024 16:31:14",
        "Download (MB)": 100.4,
        "Upload (MB)": 1.84
    },
    {
        "Hora": "28-08-2024 16:31:14",
        "Download (MB)": 106.18,
        "Upload (MB)": 2.01
    },
    {
        "Hora": "28-08-2024 16:31:15",
        "Download (MB)": 112.95,
        "Upload (MB)": 2.09
    },
    {
        "Hora": "28-08-2024 16:31:15",
        "Download (MB)": 112.42,
        "Upload (MB)": 2.13
    },
    {
        "Hora": "28-08-2024 16:31:16",
        "Download (MB)": 110.96,
        "Upload (MB)": 2.04
    },
    {
        "Hora": "28-08-2024 16:31:16",
        "Download (MB)": 110.67,
        "Upload (MB)": 1.72
    },
    {
        "Hora": "28-08-2024 16:31:17",
        "Download (MB)": 70.82,
        "Upload (MB)": 1.06
    },
    {
        "Hora": "28-08-2024 16:31:17",
        "Download (MB)": 5.14,
        "Upload (MB)": 27.98
    },
    {
        "Hora": "28-08-2024 16:31:18",
        "Download (MB)": 0.6,
        "Upload (MB)": 75.0
    },
    {
        "Hora": "28-08-2024 16:31:18",
        "Download (MB)": 0.69,
        "Upload (MB)": 106.38
    },
    {
        "Hora": "28-08-2024 16:31:19",
        "Download (MB)": 0.48,
        "Upload (MB)": 78.46
    },
    {
        "Hora": "28-08-2024 16:31:19",
        "Download (MB)": 0.18,
        "Upload (MB)": 19.34
    },
    {
        "Hora": "28-08-2024 16:31:24",
        "Download (MB)": 35.76,
        "Upload (MB)": 0.93
    },
    {
        "Hora": "28-08-2024 16:31:25",
        "Download (MB)": 75.84,
        "Upload (MB)": 1.8
    },
    {
        "Hora": "28-08-2024 16:31:25",
        "Download (MB)": 109.34,
        "Upload (MB)": 1.69
    },
    {
        "Hora": "28-08-2024 16:31:26",
        "Download (MB)": 111.24,
        "Upload (MB)": 1.6
    },
    {
        "Hora": "28-08-2024 16:31:26",
        "Download (MB)": 111.55,
        "Upload (MB)": 2.18
    },
    {
        "Hora": "28-08-2024 16:31:27",
        "Download (MB)": 111.02,
        "Upload (MB)": 2.22
    },
    {
        "Hora": "28-08-2024 16:31:27",
        "Download (MB)": 109.67,
        "Upload (MB)": 2.05
    },
    {
        "Hora": "28-08-2024 16:31:28",
        "Download (MB)": 108.1,
        "Upload (MB)": 1.96
    },
    {
        "Hora": "28-08-2024 16:31:28",
        "Download (MB)": 47.97,
        "Upload (MB)": 1.03
    },
    {
        "Hora": "28-08-2024 16:31:29",
        "Download (MB)": 8.14,
        "Upload (MB)": 4.03
    },
    {
        "Hora": "28-08-2024 16:31:29",
        "Download (MB)": 0.13,
        "Upload (MB)": 4.52
    },
    {
        "Hora": "28-08-2024 16:31:30",
        "Download (MB)": 0.28,
        "Upload (MB)": 24.25
    },
    {
        "Hora": "28-08-2024 16:31:30",
        "Download (MB)": 0.66,
        "Upload (MB)": 92.27
    },
    {
        "Hora": "28-08-2024 16:31:31",
        "Download (MB)": 0.7,
        "Upload (MB)": 110.99
    },
    {
        "Hora": "28-08-2024 16:31:31",
        "Download (MB)": 0.38,
        "Upload (MB)": 56.88
    },
    {
        "Hora": "28-08-2024 16:31:32",
        "Download (MB)": 0.15,
        "Upload (MB)": 14.7
    },
    {
        "Hora": "28-08-2024 16:31:35",
        "Download (MB)": 17.94,
        "Upload (MB)": 0.45
    },
    {
        "Hora": "28-08-2024 16:31:35",
        "Download (MB)": 82.98,
        "Upload (MB)": 1.53
    },
    {
        "Hora": "28-08-2024 16:31:36",
        "Download (MB)": 105.34,
        "Upload (MB)": 1.73
    },
    {
        "Hora": "28-08-2024 16:31:36",
        "Download (MB)": 111.68,
        "Upload (MB)": 1.36
    },
    {
        "Hora": "28-08-2024 16:31:37",
        "Download (MB)": 111.89,
        "Upload (MB)": 1.43
    },
    {
        "Hora": "28-08-2024 16:31:37",
        "Download (MB)": 112.09,
        "Upload (MB)": 1.57
    },
    {
        "Hora": "28-08-2024 16:31:38",
        "Download (MB)": 100.97,
        "Upload (MB)": 1.24
    },
    {
        "Hora": "28-08-2024 16:31:38",
        "Download (MB)": 99.45,
        "Upload (MB)": 1.4
    },
    {
        "Hora": "28-08-2024 16:31:39",
        "Download (MB)": 72.43,
        "Upload (MB)": 1.05
    },
    {
        "Hora": "28-08-2024 16:31:39",
        "Download (MB)": 2.78,
        "Upload (MB)": 12.72
    },
    {
        "Hora": "28-08-2024 16:31:40",
        "Download (MB)": 0.89,
        "Upload (MB)": 26.95
    },
    {
        "Hora": "28-08-2024 16:31:41",
        "Download (MB)": 1.74,
        "Upload (MB)": 59.04
    },
    {
        "Hora": "28-08-2024 16:31:41",
        "Download (MB)": 1.78,
        "Upload (MB)": 62.65
    },
    {
        "Hora": "28-08-2024 16:31:42",
        "Download (MB)": 1.79,
        "Upload (MB)": 62.73
    },
    {
        "Hora": "28-08-2024 16:31:42",
        "Download (MB)": 1.75,
        "Upload (MB)": 61.59
    },
    {
        "Hora": "28-08-2024 16:31:43",
        "Download (MB)": 0.57,
        "Upload (MB)": 19.24
    },
    {
        "Hora": "28-08-2024 16:31:43",
        "Download (MB)": 0.14,
        "Upload (MB)": 2.52
    },
    {
        "Hora": "28-08-2024 16:31:46",
        "Download (MB)": 3.92,
        "Upload (MB)": 0.16
    },
    {
        "Hora": "28-08-2024 16:31:47",
        "Download (MB)": 62.74,
        "Upload (MB)": 1.46
    },
    {
        "Hora": "28-08-2024 16:31:47",
        "Download (MB)": 97.5,
        "Upload (MB)": 2.19
    },
    {
        "Hora": "28-08-2024 16:31:48",
        "Download (MB)": 110.36,
        "Upload (MB)": 1.97
    },
    {
        "Hora": "28-08-2024 16:31:48",
        "Download (MB)": 109.5,
        "Upload (MB)": 1.57
    },
    {
        "Hora": "28-08-2024 16:31:49",
        "Download (MB)": 109.54,
        "Upload (MB)": 1.48
    },
    {
        "Hora": "28-08-2024 16:31:49",
        "Download (MB)": 107.74,
        "Upload (MB)": 1.71
    },
    {
        "Hora": "28-08-2024 16:31:50",
        "Download (MB)": 109.66,
        "Upload (MB)": 2.33
    },
    {
        "Hora": "28-08-2024 16:31:50",
        "Download (MB)": 95.59,
        "Upload (MB)": 2.15
    },
    {
        "Hora": "28-08-2024 16:31:51",
        "Download (MB)": 22.13,
        "Upload (MB)": 14.13
    },
    {
        "Hora": "28-08-2024 16:31:51",
        "Download (MB)": 0.31,
        "Upload (MB)": 28.24
    },
    {
        "Hora": "28-08-2024 16:31:52",
        "Download (MB)": 0.78,
        "Upload (MB)": 92.04
    },
    {
        "Hora": "28-08-2024 16:31:52",
        "Download (MB)": 0.87,
        "Upload (MB)": 109.33
    },
    {
        "Hora": "28-08-2024 16:31:53",
        "Download (MB)": 0.34,
        "Upload (MB)": 48.05
    },
    {
        "Hora": "28-08-2024 16:31:53",
        "Download (MB)": 0.13,
        "Upload (MB)": 16.14
    },
    {
        "Hora": "28-08-2024 16:32:05",
        "Download (MB)": 0.6,
        "Upload (MB)": 1.09
    },
    {
        "Hora": "28-08-2024 16:32:06",
        "Download (MB)": 1.42,
        "Upload (MB)": 2.26
    },
    {
        "Hora": "28-08-2024 16:32:06",
        "Download (MB)": 0.91,
        "Upload (MB)": 1.33
    },
    {
        "Hora": "28-08-2024 16:32:07",
        "Download (MB)": 0.6,
        "Upload (MB)": 1.18
    },
    {
        "Hora": "28-08-2024 16:32:07",
        "Download (MB)": 0.73,
        "Upload (MB)": 1.44
    },
    {
        "Hora": "28-08-2024 16:36:28",
        "Download (MB)": 23.35,
        "Upload (MB)": 0.68
    },
    {
        "Hora": "28-08-2024 16:36:28",
        "Download (MB)": 71.11,
        "Upload (MB)": 1.58
    },
    {
        "Hora": "28-08-2024 16:36:29",
        "Download (MB)": 107.73,
        "Upload (MB)": 1.74
    },
    {
        "Hora": "28-08-2024 16:36:29",
        "Download (MB)": 106.18,
        "Upload (MB)": 1.25
    },
    {
        "Hora": "28-08-2024 16:36:30",
        "Download (MB)": 101.47,
        "Upload (MB)": 1.24
    },
    {
        "Hora": "28-08-2024 16:36:30",
        "Download (MB)": 104.74,
        "Upload (MB)": 1.48
    },
    {
        "Hora": "28-08-2024 16:36:31",
        "Download (MB)": 114.79,
        "Upload (MB)": 1.67
    },
    {
        "Hora": "28-08-2024 16:36:31",
        "Download (MB)": 107.66,
        "Upload (MB)": 1.53
    },
    {
        "Hora": "28-08-2024 16:36:32",
        "Download (MB)": 62.9,
        "Upload (MB)": 0.88
    },
    {
        "Hora": "28-08-2024 16:36:32",
        "Download (MB)": 24.72,
        "Upload (MB)": 0.45
    },
    {
        "Hora": "28-08-2024 16:36:33",
        "Download (MB)": 4.35,
        "Upload (MB)": 8.65
    },
    {
        "Hora": "28-08-2024 16:36:33",
        "Download (MB)": 0.44,
        "Upload (MB)": 32.03
    },
    {
        "Hora": "28-08-2024 16:36:34",
        "Download (MB)": 0.76,
        "Upload (MB)": 78.2
    },
    {
        "Hora": "28-08-2024 16:36:34",
        "Download (MB)": 8.35,
        "Upload (MB)": 65.82
    },
    {
        "Hora": "28-08-2024 16:36:35",
        "Download (MB)": 25.95,
        "Upload (MB)": 31.35
    },
    {
        "Hora": "28-08-2024 16:36:35",
        "Download (MB)": 41.38,
        "Upload (MB)": 26.91
    },
    {
        "Hora": "28-08-2024 16:36:36",
        "Download (MB)": 61.4,
        "Upload (MB)": 15.62
    },
    {
        "Hora": "28-08-2024 16:36:36",
        "Download (MB)": 60.44,
        "Upload (MB)": 12.45
    },
    {
        "Hora": "28-08-2024 16:36:37",
        "Download (MB)": 4.76,
        "Upload (MB)": 2.02
    },
    {
        "Hora": "28-08-2024 16:36:46",
        "Download (MB)": 16.91,
        "Upload (MB)": 0.49
    },
    {
        "Hora": "28-08-2024 16:36:46",
        "Download (MB)": 74.38,
        "Upload (MB)": 1.58
    },
    {
        "Hora": "28-08-2024 16:36:47",
        "Download (MB)": 101.91,
        "Upload (MB)": 1.97
    },
    {
        "Hora": "28-08-2024 16:36:47",
        "Download (MB)": 103.39,
        "Upload (MB)": 1.52
    },
    {
        "Hora": "28-08-2024 16:36:48",
        "Download (MB)": 105.61,
        "Upload (MB)": 1.17
    },
    {
        "Hora": "28-08-2024 16:36:48",
        "Download (MB)": 103.94,
        "Upload (MB)": 1.41
    },
    {
        "Hora": "28-08-2024 16:36:49",
        "Download (MB)": 108.54,
        "Upload (MB)": 1.96
    },
    {
        "Hora": "28-08-2024 16:36:49",
        "Download (MB)": 106.31,
        "Upload (MB)": 1.91
    },
    {
        "Hora": "28-08-2024 16:36:50",
        "Download (MB)": 81.38,
        "Upload (MB)": 1.17
    },
    {
        "Hora": "28-08-2024 16:36:50",
        "Download (MB)": 26.37,
        "Upload (MB)": 2.04
    },
    {
        "Hora": "28-08-2024 16:36:51",
        "Download (MB)": 0.6,
        "Upload (MB)": 53.89
    },
    {
        "Hora": "28-08-2024 16:36:51",
        "Download (MB)": 0.68,
        "Upload (MB)": 72.06
    }
]